zope.component-6.1-py3.12-nspkg.pth
zope/component/__init__.py
zope/component/_api.py
zope/component/_compat.py
zope/component/_declaration.py
zope/component/configure.zcml
zope/component/event.py
zope/component/eventtesting.py
zope/component/factory.py
zope/component/globalregistry.py
zope/component/hooks.py
zope/component/interface.py
zope/component/interfaces.py
zope/component/meta.zcml
zope/component/persistentregistry.py
zope/component/registry.py
zope/component/security.py
zope/component/standalonetests.py
zope/component/testing.py
zope/component/testlayer.py
zope/component/zcml.py
zope/component/testfiles/__init__.py
zope/component/testfiles/adapter.py
zope/component/testfiles/components.py
zope/component/testfiles/testlayer.zcml
zope/component/testfiles/views.py
zope/component/tests/__init__.py
zope/component/tests/examples.py
zope/component/tests/test___init__.py
zope/component/tests/test__api.py
zope/component/tests/test__declaration.py
zope/component/tests/test_event.py
zope/component/tests/test_factory.py
zope/component/tests/test_globalregistry.py
zope/component/tests/test_hooks.py
zope/component/tests/test_interface.py
zope/component/tests/test_interfaces.py
zope/component/tests/test_persistentregistry.py
zope/component/tests/test_registry.py
zope/component/tests/test_security.py
zope/component/tests/test_standalone.py
zope/component/tests/test_zcml.py
zope_component-6.1.dist-info/LICENSE.txt
zope_component-6.1.dist-info/METADATA
zope_component-6.1.dist-info/WHEEL
zope_component-6.1.dist-info/namespace_packages.txt
zope_component-6.1.dist-info/top_level.txt
zope_component-6.1.dist-info/RECORD
